{
    "Relationships File": "./TestCases/RealData-Relationships.tsv",
    "Announcements File": "./TestCases/RealData-Announcements.tsv",
    "Output Folder": "./TestCases/",

    // NOTE: Do *NOT* use stub removal and origin only at the same time
    "Seeding Config": {
        // Options: true, false. Default: false
        "Origin Only": false,

        // Options: Prefer Lowest ASN, Random. Default: Prefer Lowest ASN
        "Tiebraking Method": "Prefer Lowest ASN",

        // Options: Prefer Newer, Prefer Older, Disabled. Default: Prefer Newer
        "Timestamp Comparison Method": "Prefer Newer"
    },

    // Options: true, false. Default: false
    "Stub Removal": false,

    // Options: true, false. Default: false
    "Write Results After Seeding": false,

    // Options: list of ASNs to dump tracebacks of for every prefix. Empty list will dump every AS. This is the default
    "Control Plane Traceback ASNs": []
}
